{
    "あのときの約束": "那时的约定",
    "これからが彼女たちのはじまり": "从现在开始是她们的起点",
    "で初星コミュ 第1章「第1話」解放": "解锁初星交流 第1章「第1话」",
    "ひと呼吸": "一口气",
    "アイドル選択確認": "确认选择偶像",
    "オトメゴコロ": "少女心",
    "キミとセミブルー ガシャvol": "你与半蓝 扭蛋vol",
    "スキルカードを異なるスキルカードに変え、プロデュース終了までデッキに追加（強化段階を引き継ぐ）": "将技能卡变为不同的技能卡添加到牌组中，持续到培育结束（继承强化阶段）",
    "スポットライト": "聚光灯",
    "チェンジ": "转换",
    "パラメータ+11\n○〆集中<nobr>+3</nobr>": "数值+11\n○〆集中<nobr>+3</nobr>",
    "パラメータ上昇量を50%増加": "数值上升量增加50%",
    "ブーストエキス": "增强精华",
    "個消費して\nキミとセミブルー 清夏ガシャを引きますか？": "消耗个\n你要抽取你与半蓝 清夏扭蛋吗？",
    "初星コミュ 1章": "初星交流 1章",
    "幸せのおまじない": "幸福的咒语",
    "最終考试": "最終試験",
    "止められない想い": "无法停止的想念",
    "特製ハツボシエキス": "特制初星精华",
    "立ち位置チェック": "站位检查",
    "至高のエンタメ": "至高的娱乐",
    "課題条件テキスト９０１２３４": "课题条件文本901234",
    "輝くキミへ": "向闪耀的你"
}