{
    "Dearリトルプリンス": "Dear小王子",
    "Dearリトルプリンス+": "Dear小王子+",
    "いつものメイクポーチ": "每天的化妆包",
    "いつものメイクポーチ+": "每天的化妆包+",
    "お姉さま大百科": "姐姐百科全书",
    "お気にのスニーカー": "喜欢的运动鞋",
    "お気にのスニーカー+": "喜欢的运动鞋+",
    "きみへの差し入れ": "给你的补给品",
    "きみへの差し入れ+": "给你的补给品+",
    "これが、私": "这就是我",
    "これが、私+": "这就是我+",
    "しょげないハンカチ": "不沮丧的手帕",
    "しょげないハンカチ+": "不沮丧的手帕+",
    "だれでもわかる入門書": "人人都能理解的入门书",
    "だれでもわかる入門書+": "人人都能理解的入门书+",
    "ちびども手作りメダル": "小家伙们自制的勋章",
    "ちびども手作りメダル+": "小家伙们自制的勋章+",
    "はつぼしTシャツ": "初星T恤",
    "はつぼしキーホルダー": "初星钥匙链",
    "はつぼしブレスレット": "初星手链",
    "はつぼしブローチ": "初星胸针",
    "はつぼし手帳": "初星手账",
    "ばくおんライオン": "猛狮咆哮",
    "ばくおんライオン+": "猛狮咆哮+",
    "ひみつ特訓カーデ": "秘密特训开衫",
    "ひみつ特訓カーデ+": "秘密特训开衫+",
    "ふわふわでもこもこ": "蓬松又胖胖",
    "みちくさ研究ノート": "小道研究笔记",
    "みちくさ研究ノート+": "小道研究笔记+",
    "ゲーセンの戦利品": "游戏中心的战利品",
    "ゲーセンの戦利品+": "游戏中心的战利品+",
    "スカウト遮り帽": "侦查遮挡帽",
    "ダブルボトル": "双瓶",
    "テクノドッグ": "科技狗",
    "テクノドッグ+": "科技狗+",
    "ピッグドリーム貯金箱": "猪梦储蓄罐",
    "ピッグドリーム貯金箱+": "猪梦储蓄罐+",
    "ピンクのお揃いブレス": "粉色的情侣手链",
    "ピンクのお揃いブレス+": "粉色的情侣手链+",
    "マスコット（非公認）": "吉祥物（非公认）",
    "一緒にお昼寝ポプリ": "一起小憩的香草",
    "仲直りのきっかけ": "和解的契机",
    "例のSSDの秘密": "那个SSD的秘密",
    "信頼の証": "信赖的证明",
    "共に戦うタオル": "一起战斗的毛巾",
    "共に戦うタオル+": "一起战斗的毛巾+",
    "内なる光の耳飾り": "内心之光的耳饰",
    "内なる光の耳飾り+": "内心之光的耳饰+",
    "勝ちへのこだわり": "对胜利的执着",
    "勝ちへのこだわり+": "对胜利的执着+",
    "咲季の完全食レシピ": "咲季的完全食谱",
    "咲季の完全食レシピ+": "咲季的完全食谱+",
    "夢にあふれた大荷物": "充满梦想的大行李",
    "夢へのライフログ": "通往梦想的生活日志",
    "夢へのライフログ+": "通往梦想的生活日志+",
    "天川ラーメン巡り": "天川拉面巡游",
    "得体のしれないモノ": "无法理解的东西",
    "必携ステンレスボトル": "必备不锈钢水瓶",
    "必携ステンレスボトル+": "必备不锈钢水瓶+",
    "思い出ロボ": "回忆机器人",
    "思い出ロボ+": "回忆机器人+",
    "悔しさの象徴": "悔恨的象征",
    "手作りのご褒美": "手工制作的奖励",
    "打倒！墾田永年私財法": "打倒！垦田永年私财法",
    "放課後のらくがき": "放学后的涂鸦",
    "放課後のらくがき+": "放学后的涂鸦+",
    "星のリトルプリンス": "星星的小王子",
    "曇りをぬぐったタオル": "拭去阴霾的毛巾",
    "最高にハッピーの源": "至高快乐的源泉",
    "最高にハッピーの源+": "至高快乐的源泉+",
    "朝一の助け舟": "早晨的救助舟",
    "柴犬ポシェット": "柴犬邮差包",
    "柴犬ポシェット+": "柴犬邮差包+",
    "満開ペアヘアピン": "盛开配对发夹",
    "私が見つけた逸材メモ": "我发现的优秀人才备忘",
    "私の「初」の楽譜": "我的“初”乐谱",
    "私の「初」の楽譜+": "我的“初”乐谱+",
    "等身大のレディリップ": "等身大的女士唇",
    "等身大のレディリップ+": "等身大的女士唇+",
    "紳士風ハンカチーフ": "绅士风格手帕",
    "紳士風ハンカチーフ+": "绅士风格手帕+",
    "緑のお揃いブレス": "绿色同款手链",
    "緑のお揃いブレス+": "绿色同款手链+",
    "美鈴からの贈り物": "来自美铃的礼物",
    "自分を守るイヤホン": "保护自己的耳机",
    "自分を守るイヤホン+": "保护自己的耳机+",
    "虹かけるクロス": "架起彩虹的十字",
    "誓いの花びら": "誓言的花瓣",
    "超絶あんみんマスク": "超绝安眠面膜",
    "超絶あんみんマスク+": "超绝安眠面膜+",
    "転がり続ける元気の源": "不断滚动的元气源泉",
    "転がり続ける元気の源+": "不断滚动的元气源泉+",
    "願いを叶えるお守り": "实现愿望的护身符",
    "願いを叶えるお守り+": "实现愿望的护身符+"
}